gq/__init__.py
gq/gqs1.py
gq/gqs1_core.py
gq/universal_qkd.py
gq/cli/__init__.py
gq/cli/gqs1.py
gq/cli/universal.py
golden_quantum-1.0.0.dist-info/METADATA
golden_quantum-1.0.0.dist-info/WHEEL
golden_quantum-1.0.0.dist-info/entry_points.txt
golden_quantum-1.0.0.dist-info/top_level.txt
golden_quantum-1.0.0.dist-info/RECORD
