Metadata-Version: 2.4
Name: golden-quantum
Version: 1.0.0
Summary: Universal Golden Seed Consensus Protocol (GCP-1 & GQS-1)
Home-page: https://github.com/beanapologist/seed
Author: beanapologist
Project-URL: Bug Reports, https://github.com/beanapologist/seed/issues
Project-URL: Source, https://github.com/beanapologist/seed
Project-URL: Documentation, https://github.com/beanapologist/seed#readme
Keywords: quantum cryptography consensus blockchain deterministic qkd gcp gqs
Classifier: Development Status :: 5 - Production/Stable
Classifier: Intended Audience :: Developers
Classifier: Topic :: Security :: Cryptography
Classifier: Topic :: Software Development :: Libraries :: Python Modules
Classifier: Programming Language :: Python :: 3
Classifier: Programming Language :: Python :: 3.8
Classifier: Programming Language :: Python :: 3.9
Classifier: Programming Language :: Python :: 3.10
Classifier: Programming Language :: Python :: 3.11
Classifier: Programming Language :: Python :: 3.12
Classifier: License :: OSI Approved :: MIT License
Classifier: Operating System :: OS Independent
Requires-Python: >=3.8
Provides-Extra: dev
Requires-Dist: pytest>=7.0; extra == "dev"
Requires-Dist: pytest-cov>=4.0; extra == "dev"
Dynamic: author
Dynamic: classifier
Dynamic: description
Dynamic: description-content-type
Dynamic: home-page
Dynamic: keywords
Dynamic: project-url
Dynamic: provides-extra
Dynamic: requires-python
Dynamic: summary
